paspybin/__init__.py
paspybin/api/__init__.py
paspybin/api/api.py
paspybin/api/paspybin.py
paspybin/api/paste.py
paspybin/api/pastes.py
paspybin/api/user.py
paspybin/enums/__init__.py
paspybin/enums/expire.py
paspybin/enums/format.py
paspybin/enums/type.py
paspybin/enums/visibility.py
paspybin/exceptions.py
paspybin/parsers.py
paspybin/py.typed
paspybin/schemas/__init__.py
paspybin/schemas/paste.py
paspybin/schemas/user.py
paspybin/types.py
paspybin-1.1.0.dist-info/LICENSE
paspybin-1.1.0.dist-info/METADATA
paspybin-1.1.0.dist-info/WHEEL
paspybin-1.1.0.dist-info/RECORD
