Metadata-Version: 2.1
Name: paspybin
Version: 1.1.0
Summary: Python Pastebin API Wrapper
Home-page: https://github.com/kiraware/paspybin
License: MIT
Keywords: pastebin,api
Author: Kira
Author-email: kiraware@github.com
Maintainer: Kira
Maintainer-email: kiraware@github.com
Requires-Python: >=3.11,<4.0
Classifier: Development Status :: 5 - Production/Stable
Classifier: Environment :: Web Environment
Classifier: Framework :: AsyncIO
Classifier: Framework :: aiohttp
Classifier: Intended Audience :: Developers
Classifier: License :: OSI Approved :: MIT License
Classifier: Operating System :: OS Independent
Classifier: Programming Language :: Python :: 3
Classifier: Programming Language :: Python :: 3.11
Classifier: Programming Language :: Python :: 3.12
Classifier: Programming Language :: Python :: 3.13
Classifier: Topic :: Software Development
Requires-Dist: aiohttp (>=3.9.1,<4.0.0)
Requires-Dist: defusedxml (>=0.7.1,<0.8.0)
Requires-Dist: types-defusedxml (>=0.7.0.20240218,<0.8.0.0)
Project-URL: Bug Tracker, https://github.com/kiraware/paspybin/issues
Project-URL: Documentation, https://paspybin.readthedocs.io/en/latest/
Project-URL: Repository, https://github.com/kiraware/paspybin
